magento/__init__.py
magento/clients.py
magento/exceptions.py
magento/search.py
magento/utils.py
magento/models/__init__.py
magento/models/category.py
magento/models/customer.py
magento/models/invoice.py
magento/models/model.py
magento/models/order.py
magento/models/product.py
my_magento-2.2.0.dist-info/LICENSE
my_magento-2.2.0.dist-info/METADATA
my_magento-2.2.0.dist-info/WHEEL
my_magento-2.2.0.dist-info/top_level.txt
my_magento-2.2.0.dist-info/RECORD
