Metadata-Version: 2.1
Name: my-magento
Version: 2.2.0
Summary: Python Magento 2 REST API Wrapper
Home-page: https://www.github.com/TDKorn/my-magento
Author: Adam Korn
Author-email: hello@dailykitten.net
License: MIT
Download-URL: https://github.com/TDKorn/my-magento/tarball/master
Keywords: magento,magento-api,python-magento,python,python3,magento-python,pymagento,py-magento,magento2,magento-2,magento2-api
Platform: UNKNOWN
License-File: LICENSE
Requires-Dist: requests
